polars_splines-0.1.2.dist-info/METADATA
polars_splines-0.1.2.dist-info/WHEEL
polars_splines-0.1.2.dist-info/licenses/LICENSE
polars_splines/__init__.py
polars_splines/polars_splines.pypy310-pp73-ppc_64-linux-gnu.so
polars_splines-0.1.2.dist-info/RECORD
