Metadata-Version: 2.3
Name: polars-splines
Version: 0.1.2
Classifier: License :: OSI Approved :: MIT License
Classifier: Programming Language :: Python :: 3
Requires-Dist: polars >=1.7, <2
License-File: LICENSE
Summary: A polars expression plugin for splines
Keywords: splines,interpolation,polars
Author-email: Mattias Matthiesen <mattmatthi@gmail.com>
Requires-Python: >=3.10
